{
    "list": [
        {
            "name": "Baloncesto"
        },
        {
            "name": "Balonmano"
        },
        {
            "name": "Béisbol"
        },
        {
            "name": "BMX"
        },
        {
            "name": "Calistenia"
        },
        {
            "name": "Ciclismo"
        },
        {
            "name": "Estiramientos"
        },
        {
            "name": "Fútbol"
        },
        {
            "name": "Kayak"
        },
        {
            "name": "Marcha atlética"
        },
        {
            "name": "Natación"
        },
        {
            "name": "Marcha nórdica"
        },
        {
            "name": "Paddlesurf"
        },
        {
            "name": "Parque de ejercicios"
        },
        {
            "name": "Patinaje"
        },
        {
            "name": "Petanca"
        },
        {
            "name": "Remo"
        },
        {
            "name": "Correr"
        },
        {
            "name": "Skate"
        },
        {
            "name": "Surf"
        },
        {
            "name": "Navegación"
        },
        {
            "name": "Voleibol"
        },
        {
            "name": "Windsurf"
        },
        {
            "name": "Parkour"
        },
        {
            "name": "Yoga"
        }
    ]
}